garmin_ace/__init__.py
garmin_ace/constants.py
garmin_ace/convert.py
garmin_ace/decoder.py
garmin_ace/encoder.py
garmin_ace/models.py
garmin_ace/utils.py
html/style.css
garmin_ace-0.0.1a10.dist-info/METADATA
garmin_ace-0.0.1a10.dist-info/WHEEL
garmin_ace-0.0.1a10.dist-info/entry_points.txt
garmin_ace-0.0.1a10.dist-info/licenses/LICENSE
garmin_ace-0.0.1a10.dist-info/RECORD
