Metadata-Version: 2.1
Name: garmin_ace
Version: 0.0.1a10
Summary: Garmin Aviation Checklist Editor (ACE) - Parse and write ACE files from Python
Project-URL: Homepage, https://gitlab.com/antoviaque/garmin-ace
Project-URL: Bug Tracker, https://gitlab.com/antoviaque/garmin-ace/-/issues
Author-email: Xavier Antoviaque <xavier@antoviaque.org>
License-File: LICENSE
Classifier: License :: OSI Approved :: GNU Affero General Public License v3
Classifier: Operating System :: OS Independent
Classifier: Programming Language :: Python :: 3
Requires-Python: >=3.7
Requires-Dist: orgparse
